sigexport/__init__.py
sigexport/__main__.py
sigexport/create.py
sigexport/crypto.py
sigexport/data.py
sigexport/files.py
sigexport/html.py
sigexport/logging.py
sigexport/main.py
sigexport/merge.py
sigexport/models.py
sigexport/style.css
sigexport/templates.py
sigexport/utils.py
signal_export-2.4.1.dist-info/METADATA
signal_export-2.4.1.dist-info/WHEEL
signal_export-2.4.1.dist-info/entry_points.txt
signal_export-2.4.1.dist-info/licenses/LICENSE
signal_export-2.4.1.dist-info/RECORD
