Metadata-Version: 2.1
Name: signal-export
Version: 2.4.1
Summary: Export Signal conversations to Markdown and HTML
Keywords: backup,chat,export
Home-page: https://github.com/carderne/signal-export
Author-Email: Chris Arderne <chris@rdrn.me>
License: MIT License
Classifier: Environment :: Console
Classifier: License :: OSI Approved :: MIT License
Classifier: Operating System :: Unix
Classifier: Programming Language :: Python
Project-URL: Homepage, https://github.com/carderne/signal-export
Project-URL: Repository, https://github.com/carderne/signal-export
Requires-Python: >=3.9
Requires-Dist: beautifulsoup4~=4.11
Requires-Dist: emoji~=2.0
Requires-Dist: Markdown~=3.4
Requires-Dist: typer[all]~=0.7
Requires-Dist: pycryptodome~=3.20.0
Requires-Dist: pysqlcipher3==1.1.0; python_version < "3.11" and extra == "sql"
Requires-Dist: pysqlcipher3>=1.2.0; python_version >= "3.11" and extra == "sql"
Provides-Extra: sql
